{
  "version": "v1",
  "maxYearsExperience": 25,
  "maxSalaryExpectation": 300000,
  "maxLanguageCount": 6,
  "knownLocations": [
    "sao paulo",
    "rio de janeiro",
    "belo horizonte",
    "remote",
    "florianopolis",
    "curitiba",
    "porto alegre",
    "recife",
    "toronto",
    "campinas",
    "berlin"
  ],
  "knownSkills": [
    "node.js",
    "typescript",
    "postgresql",
    "redis",
    "kafka",
    "react",
    "vite",
    "tailwind css",
    "testing library",
    "graphql",
    "sql",
    "apache spark",
    "c#",
    "java",
    "spring boot",
    "kubernetes",
    "rabbitmq",
    "docker",
    "terraform",
    "aws",
    "prometheus",
    "go",
    "grpc",
    "bloc",
    "flutter",
    "rest api",
    "firebase",
    "python",
    "pytorch",
    "swift",
    "swiftui",
    "xcode",
    "core data",
    "uikit",
    "kotlin",
    "jetpack compose",
    "android sdk",
    "room",
    "coroutines",
    "erlang",
    "ecto",
    "liveview",
    "phoenix",
    "apache airflow",
    ".net",
    "sql server",
    "azure",
    "dart",
    "scikit-learn",
    "mlflow",
    "jest",
    "playwright",
    "cypress",
    "elixir",
    "ci/cd"
  ],
  "knownTitles": [
    "backend engineer",
    "software engineer",
    "frontend engineer",
    "react developer",
    "fullstack engineer",
    "tech lead",
    "python engineer",
    "backend developer",
    "platform engineer",
    "software architect",
    "devops engineer",
    "site reliability engineer",
    "mobile engineer",
    "flutter developer",
    "data scientist",
    "qa engineer",
    "ios developer",
    "android developer",
    "elixir developer",
    "data engineer",
    "machine learning engineer",
    "software engineer in test"
  ],
  "knownLanguages": [
    "english",
    "portuguese",
    "german"
  ],
  "knownNoticePeriods": [
    "30 days",
    "15 days",
    "45 days",
    "60 days",
    "immediate"
  ],
  "seniorityCategories": [
    "intern",
    "junior",
    "mid",
    "senior",
    "staff",
    "principal"
  ],
  "workModelCategories": [
    "remote",
    "hybrid",
    "on-site"
  ],
  "contractTypeCategories": [
    "clt",
    "pj",
    "freelance",
    "contract",
    "full-time",
    "part-time"
  ]
}